probequest/__init__.py
probequest/__main__.py
probequest/cli.py
probequest/config.py
probequest/exceptions.py
probequest/probe_request.py
probequest/probe_request_filter.py
probequest/probe_request_parser.py
probequest/exporters/__init__.py
probequest/exporters/csv.py
probequest/sniffers/__init__.py
probequest/sniffers/fake_probe_request_sniffer.py
probequest/sniffers/probe_request_sniffer.py
probequest/ui/__init__.py
probequest/ui/console.py
probequest-0.8.0.dist-info/LICENSE
probequest-0.8.0.dist-info/METADATA
probequest-0.8.0.dist-info/WHEEL
probequest-0.8.0.dist-info/entry_points.txt
probequest-0.8.0.dist-info/top_level.txt
probequest-0.8.0.dist-info/RECORD
