Metadata-Version: 2.1
Name: probequest
Version: 0.8.0
Summary: Toolkit for Playing with Wi-Fi Probe Requests.
Home-page: https://github.com/SkypLabs/probequest
Author: Paul-Emmanuel Raoul
Author-email: skyper@skyplabs.net
License: GPLv3
Project-URL: Bug Tracker, https://github.com/SkypLabs/probequest/issues
Project-URL: Documentation, https://probequest.readthedocs.io
Project-URL: Source Code, https://github.com/SkypLabs/probequest
Keywords: wifi,wireless,security,sniffer
Platform: UNKNOWN
Classifier: Development Status :: 4 - Beta
Classifier: Environment :: Console
Classifier: Intended Audience :: Information Technology
Classifier: Natural Language :: English
Classifier: Topic :: Security
Classifier: Topic :: System :: Networking
Classifier: Topic :: System :: Networking :: Monitoring
Classifier: Programming Language :: Python :: 3 :: Only
Classifier: Programming Language :: Python :: 3.7
Classifier: Programming Language :: Python :: 3.8
Classifier: Programming Language :: Python :: 3.9
Classifier: Programming Language :: Python :: 3.10
Classifier: License :: OSI Approved :: GNU General Public License v3 (GPLv3)
Requires-Python: <4,>=3.7
License-File: LICENSE
Requires-Dist: netaddr (>=0.7.19)
Requires-Dist: scapy (>=2.4.3)
Provides-Extra: complete
Requires-Dist: faker-wifi-essid ; extra == 'complete'
Provides-Extra: docs
Requires-Dist: Sphinx (>=3.2) ; extra == 'docs'
Requires-Dist: sphinxcontrib-seqdiag (>=2.0.0) ; extra == 'docs'
Requires-Dist: sphinx-argparse (>=0.2.2) ; extra == 'docs'
Requires-Dist: sphinx-rtd-theme (>=0.5.0) ; extra == 'docs'
Provides-Extra: tests
Requires-Dist: flake8 ; extra == 'tests'
Requires-Dist: pylint ; extra == 'tests'
Requires-Dist: tox ; extra == 'tests'
